README.md
setup.py
forexportal/__init__.py
forexportal/api.py
forexportal/errors.py
forexportal/schemas.py
forexportal_api.egg-info/PKG-INFO
forexportal_api.egg-info/SOURCES.txt
forexportal_api.egg-info/dependency_links.txt
forexportal_api.egg-info/not-zip-safe
forexportal_api.egg-info/requires.txt
forexportal_api.egg-info/top_level.txt