Metadata-Version: 2.1
Name: forexportal-api
Version: 0.2
Summary: Forex Portal API
Home-page: https://github.com/btfspace/forexportal-api
Author-email: me@biteof.space
License: UNKNOWN
Platform: UNKNOWN
Classifier: Programming Language :: Python :: 3
Classifier: License :: OSI Approved :: MIT License
Classifier: Operating System :: OS Independent
